ptt2json/__init__.py
ptt2json-0.1.1.dist-info/WHEEL
ptt2json-0.1.1.dist-info/METADATA
ptt2json-0.1.1.dist-info/RECORD
