Metadata-Version: 2.1
Name: ptt2json
Version: 0.1.1
Summary: A simple python library to extract pages and posts information from https://www.ptt.cc/bbs/ to json format
Home-page: https://github.com/LImoritakeU/ptt2json
Keywords: ptt
Author: LImoritakeU
Author-email: LImoritakeU@gmail.com
Requires-Python: >=3.6,<4.0
Classifier: Programming Language :: Python :: 3
Classifier: Programming Language :: Python :: 3.6
Classifier: Programming Language :: Python :: 3.7
Requires-Dist: pyquery (>=1.4,<2.0)
Requires-Dist: requests (>=2.22,<3.0)
